nonebot_plugin_inspect-0.2.0.dist-info/METADATA
nonebot_plugin_inspect-0.2.0.dist-info/WHEEL
nonebot_plugin_inspect-0.2.0.dist-info/entry_points.txt
nonebot_plugin_inspect-0.2.0.dist-info/licenses/LICENSE
nonebot_plugin_inspect/__init__.py
nonebot_plugin_inspect/i18n/.config.json
nonebot_plugin_inspect/i18n/.lang.schema.json
nonebot_plugin_inspect/i18n/.template.json
nonebot_plugin_inspect/i18n/.template.schema.json
nonebot_plugin_inspect/i18n/__init__.py
nonebot_plugin_inspect/i18n/de-DE.json
nonebot_plugin_inspect/i18n/en-US.json
nonebot_plugin_inspect/i18n/fr-FR.json
nonebot_plugin_inspect/i18n/ja-JP.json
nonebot_plugin_inspect/i18n/model.py
nonebot_plugin_inspect/i18n/ru-RU.json
nonebot_plugin_inspect/i18n/zh-CN.json
nonebot_plugin_inspect/i18n/zh-TW.json
nonebot_plugin_inspect-0.2.0.dist-info/RECORD
